{"board": [["B", "U", "N", "C", "H", "E"], ["F", "L", "A", "K", "E", "R"], ["F", "U", "T", "Z", "E", "S"], ["T", "Y", "R", "O", "N", "E"], ["D", "E", "F", "U", "Z", "E"], ["R", "E", "M", "A", "S", "K"], ["B", "A", "R", "F", "L", "Y"]], "valid": ["hers", "merd", "dree", "eyr", "rea", "reef", "buncher", "mear", "erd", "flakers", "laker", "trone", "here", "aer", "reen", "rear", "her", "lunchers", "ere", "seer", "drear", "neer", "eer", "frozen", "ear", "esr", "senor", "remask", "taker", "bree", "rone", "flaker", "ree", "armer", "naker", "reese", "tyrone", "erse", "kers", "breed", "rye", "reh", "reed", "takers", "merde", "herse", "abreed", "frouze", "luncher", "ers", "frae", "rearm", "froze", "orfe", "rem", "mer", "feer", "deer", "frye", "lakers", "trones"], "invalid": ["yulan", "che", "seek", "natron", "buna", "yed", "barf", "flanche", "luff", "take", "tyr", "uta", "mask", "ort", "yee", "lutzen", "ful", "nee", "nou", "meed", "latron", "nor", "amra", "cheese", "luta", "fed", "fut", "sly", "tal", "zee", "latry", "bunche", "akee", "zone", "bulak", "def", "hee", "tula", "deem", "flub", "sene", "abr", "alf", "lunch", "fuye", "see", "zek", "sen", "fame", "fas", "lake", "natr", "fuzees", "zeks", "bar", "ron", "een", "flu", "tuy", "mas", "defuze", "dee", "fula", "ouze", "akees", "unal", "lub", "skeen", "fly", "ame", "tulu", "chekan", "bae", "flak", "fuze", "afl", "barm", "tan", "nul", "unc", "ake", "same", "tryt", "sky", "emf", "dey", "ask", "tyee", "mau", "fuzee", "ula", "futzes", "frab", "auf", "one", "nat", "tye", "flan", "fro", "ones", "lanch", "fra", "zones", "fey", "ouf", "orf", "ameed", "rab", "kyl", "ezo", "tufty", "sam", "nub", "zeno", "fam", "flanch", "zees", "tyro", "yuft", "lak", "ene", "tuft", "kees", "fry", "tron", "asl", "arm", "tuff", "flat", "ory", "nake", "fluyt", "natu", "ulu", "frt", "keen", "skee", "bun", "luna", "bunch", "seeks", "lat", "kat", "atry", "try", "trf", "nese", "ese", "sauf", "lan", "anu", "chee", "latro", "zen", "futz", "flake", "nak", "fee", "kan", "lut", "barfly"], "rule_text": "directions: E W N S  -- What's in dem words. Is it: e and r. Yeah it is. -- ", "time_s": 324.0, "text_fully_revealed_at_s": 90, "number_of_words": 6, "uniqueness": 0.54, "difficulty": 768.5}