{"board": [["M", "E", "A"], ["S", "A", "R"], ["P", "E", "O"], ["T", "Z", "U"], ["D", "N", "W"], ["I", "X", "Q"], ["A", "U", "S"]], "valid": ["orae", "meas", "eas", "aid", "aix", "oras", "ear", "dix", "roe", "asmear", "ara", "sar", "psa", "pea", "pear", "dia", "asp", "zep", "ras", "rasp", "ora", "zea", "mear", "smear", "spear", "ouze", "peas", "aras", "spt"], "invalid": [], "rule_text": "directions: E W N S  -- ", "time_s": 648.0, "text_fully_revealed_at_s": 90, "number_of_words": 8, "uniqueness": 0.0, "difficulty": 937.0}