{"board": [["O", "E", "J", "M", "L", "O"], ["R", "E", "E", "R", "E", "E"], ["I", "E", "H", "A", "R", "E"], ["K", "N", "A", "G", "I", "V"], ["O", "T", "L", "N", "E", "U"], ["O", "I", "I", "I", "N", "V"]], "valid": ["gane", "revie", "nei", "vire", "gari", "lan", "nag", "agni", "ragi", "aln", "rerig", "veri", "gie", "gien", "ane", "lane", "kie", "alii", "hagi", "eire", "nagari", "knee", "ali", "gire", "hare", "ning", "ive", "hankie", "arere", "hen", "hei", "reen", "ire", "vie", "enki", "gare", "lee", "ore", "gan", "oki", "han", "nagi", "iii", "vignin", "lii", "hag", "ree", "ingan", "rive", "jee", "ine", "liin", "give", "rig", "eerie", "revue", "ole", "rie", "ign", "roe", "knag", "lere", "erie", "ere", "nine", "rag", "reree", "vee", "eole", "nee", "hee", "ing", "here", "rare", "are", "een", "anti", "gali", "lag", "oii"], "invalid": ["elm", "giver", "eir", "arm", "nga", "riv", "eel", "ler", "harm", "agal", "enl", "neer", "galt", "lank", "gal", "env", "ent", "riga", "reh", "her", "olm", "kir", "inla", "eer", "too", "ingiver", "heir", "agar", "herm", "viga", "jeer", "rel", "vera", "lah", "ant", "raga", "rev", "inv", "hera", "lant", "jerm", "alto", "ira", "aha", "hank", "naga", "gneu", "hant", "iga", "orient", "era", "gareh", "inga", "ningal", "heer", "hent", "eira", "lahar", "gant", "aga", "erer", "alt", "gar", "halt", "rah"], "rule_text": "directions: E W N S  -- Ends with a letter from wedding -- ", "time_s": 1296.0, "text_fully_revealed_at_s": 90, "number_of_words": 18, "uniqueness": 0.5335570469798657, "difficulty": 945.5}