{"board": [["H", "S", "L", "A", "N", "H", "E"], ["P", "E", "T", "N", "L", "E", "H"], ["H", "E", "A", "N", "T", "L", "P"], ["S", "L", "A", "A", "I", "A", "N"], ["A", "E", "R", "N", "W", "N", "A"], ["U", "N", "D", "N", "U", "A", "G"], ["A", "E", "I", "U", "S", "O", "L"]], "valid": ["nei", "phs", "unn", "wun", "ean", "lpn", "ern", "tan", "pes", "gao", "ann", "eln", "eas", "arn", "nan", "als", "ian", "sun", "lai", "wus", "els", "lan", "gan"], "invalid": ["slare", "lant", "rend", "nael", "renu", "aer", "natl", "sunna", "ial", "tee", "sheet", "usu", "sla", "shee", "annates", "anti", "erd", "arna", "aals", "diener", "she", "wunna", "slant", "gaus", "annals", "gaun", "shp", "aeneid", "etna", "annus", "asl", "anre", "ate", "eral", "antae", "nale", "lare", "lene", "tia", "nerd", "taa", "tanti", "sheep", "ausu", "nantes", "sle", "sleep", "ard", "lantana", "eeler", "ait", "helen", "alenu", "sep", "lar", "elt", "nea", "hela", "arend", "shea", "leat", "rals", "sleet", "nat", "tael", "ana", "suid", "lee", "gaol", "taal", "eta", "rale", "ant", "aare", "nana", "tanan", "aune", "aaa", "lend", "hee", "slt", "lees", "era", "aeneas", "leet", "rel", "slee", "taar", "ash", "rna", "are", "naiant", "larn", "sunn", "heh", "tesla", "eat", "alt", "loa", "ates", "plait", "sol", "neral", "ashe", "ela", "area", "nanna", "antes", "naos", "pee", "tantle", "rea", "alen", "hel", "aal", "help", "eel", "seel", "ale", "leep", "tae", "nagana", "areas", "eels", "pet", "nag", "asleep", "shean", "iana", "leant", "gau", "naa", "alp", "anal", "nates", "tana", "tanna", "anan", "iaa", "nra", "setae", "heat", "wit", "aga", "nae", "aren", "annal", "lard", "shela", "seels", "aar", "leash", "peels", "nnw", "naga", "peel", "nantle", "alee", "end", "see", "die", "hele", "eneid", "loan", "anana", "nant", "set", "ene", "sheat", "plan", "anta", "raanan", "seta", "lea", "anna", "annat", "taels", "lean", "ante", "teels", "sundra", "elan", "diene", "ler", "peele", "peeler", "teel"], "rule_text": "directions: E W N S  -- At least 3 of da letters. -- OMG, ends with a letter from: minos -- ", "time_s": 432.0, "text_fully_revealed_at_s": 90, "number_of_words": 6, "uniqueness": 0.5175126952559326, "difficulty": 963.5}