{"board": [["T", "R", "O", "P", "A", "L"], ["E", "N", "V", "E", "I", "L"], ["M", "E", "Z", "A", "I", "L"], ["B", "U", "R", "L", "A", "P"], ["P", "E", "L", "V", "I", "C"], ["W", "I", "N", "O", "E", "S"], ["S", "L", "A", "R", "T", "H"], ["U", "N", "R", "U", "E", "D"], ["F", "A", "G", "O", "T", "S"]], "valid": ["argo", "euro", "veil", "oran", "noes", "teds", "aiai", "gran", "rani", "agra", "port", "porn", "peal", "true", "pall", "oral", "alae", "rope", "lieu", "anil", "lino", "wino", "veal", "vial", "roes", "urth", "toga", "anus", "pail", "tour", "tets", "opal", "teth", "icsh", "seth", "burl", "urga"], "invalid": ["mene", "lvi", "ort", "pel", "sht", "emeu", "urals", "tourte", "uran", "via", "ial", "peai", "ina", "funli", "met", "metro", "gra", "ourn", "seor", "rle", "sla", "gour", "vlei", "mezail", "urali", "lin", "zen", "eths", "stour", "suf", "nil", "ruen", "vies", "art", "aln", "lnr", "meu", "arna", "tenez", "tourt", "env", "gote", "ted", "tropal", "pei", "pli", "gou", "eon", "fagots", "ail", "lie", "enveil", "ural", "lan", "unrued", "gan", "ourali", "agral", "voet", "fag", "rued", "stet", "urna", "lar", "nro", "aru", "embue", "leu", "alnus", "novial", "burlap", "fagoted", "pelvics", "norths", "rals", "fun", "pea", "apc", "rub", "men", "pein", "fagot", "ten", "eth", "laic", "ill", "opai", "trona", "fan", "eln", "thd", "tet", "alvia", "ona", "als", "urn", "ran", "oni", "argan", "sun", "argot", "argots", "rna", "grano", "ote", "alin", "aport", "rural", "anorth", "nor", "larn", "tetra", "tete", "lep", "naf", "eme", "ics", "cpa", "palli", "oes", "lii", "tog", "laron", "all", "ufa", "trop", "ani", "laics", "nov", "voe", "pelvic", "ago", "ortet", "got", "ron", "epa", "civ", "bur", "lap", "grue", "rte", "nag", "slarth", "arn", "ali", "tra", "ura", "largo", "vei", "lina", "trope", "seora", "nar", "edh", "detour", "ope", "voes", "eds", "trued", "net", "nra", "ape", "tou", "north", "ala", "stoga", "cia", "ora", "vie", "edhs", "cse", "anu", "ein", "winoes", "rove", "pal", "tourn", "roe", "unlie", "stog", "win", "ene", "set", "teths", "trove", "lei", "eila", "url", "tron", "porte", "unrural", "our", "lai", "lieue", "unl", "laevo", "rue", "orals", "slart", "anils", "ano", "zeme", "laze"], "rule_text": "directions: E W N S  -- No more no less than the best which is 4. -- OMG,these are: nouns -- ", "time_s": 792.0, "text_fully_revealed_at_s": 90, "number_of_words": 11, "uniqueness": 0.7728583970901793, "difficulty": 988.0}