{
  "board": [
    [
      "O",
      "I",
      "U",
      "L"
    ],
    [
      "S",
      "I",
      "I",
      "E"
    ],
    [
      "C",
      "F",
      "E",
      "L"
    ],
    [
      "E",
      "M",
      "N",
      "N"
    ],
    [
      "A",
      "S",
      "A",
      "E"
    ],
    [
      "E",
      "O",
      "A",
      "E"
    ]
  ],
  "valid": [
    "man",
    "feel",
    "seam",
    "alien",
    "seel",
    "seen",
    "loosen",
    "enamel",
    "sic",
    "mean",
    "lean",
    "clean",
    "manes",
    "soles",
    "anneal",
    "seem"
  ],
  "invalid": [
    "sence",
    "lene",
    "filao",
    "meile",
    "salience",
    "samen",
    "ansa",
    "cise",
    "enaena",
    "ase",
    "neal",
    "nee",
    "oasean",
    "nanes",
    "men",
    "nan",
    "sife",
    "enlief",
    "saulie",
    "sloe",
    "melee",
    "slue",
    "manse",
    "amen",
    "fise",
    "fennel",
    "mesal",
    "alo",
    "salse",
    "mense",
    "sceneman",
    "salele",
    "sou",
    "aloe",
    "sluice",
    "nae",
    "losel",
    "sice",
    "sen",
    "leman",
    "life",
    "feasance",
    "siol",
    "sele",
    "filo",
    "filose",
    "sale",
    "islesman",
    "lieu",
    "mana",
    "mel",
    "neif",
    "oleose",
    "saa",
    "meece",
    "asale",
    "file",
    "feme",
    "ule",
    "fels",
    "nei",
    "lief",
    "naa",
    "masoola",
    "lees",
    "aenean",
    "alee",
    "mease",
    "clef",
    "lieue",
    "ama",
    "mao",
    "fen",
    "cee",
    "fenman",
    "sial",
    "feis",
    "ease",
    "emcee",
    "fei",
    "lea",
    "mesa",
    "aal",
    "eme",
    "eoan",
    "nema",
    "nane",
    "feil",
    "aisle",
    "anam",
    "ife",
    "samel",
    "ceile",
    "lile",
    "loo",
    "senna",
    "smee",
    "cisele",
    "laiose",
    "soam",
    "melena",
    "slae",
    "alesan",
    "oii",
    "nael",
    "ann",
    "oleana",
    "ana",
    "sai",
    "same",
    "else",
    "masa",
    "cleam",
    "saman",
    "manei",
    "naos",
    "seise",
    "auloi",
    "neem",
    "semence",
    "fie",
    "amaas",
    "ensoul",
    "iceman",
    "leam",
    "isle",
    "las",
    "lease",
    "lien",
    "neele",
    "aalii",
    "sla",
    "sane",
    "seme",
    "sienna",
    "lai",
    "slee",
    "aiel",
    "oam",
    "sec",
    "soleil",
    "iso",
    "mae",
    "solea",
    "scena",
    "loose",
    "mese",
    "enseam",
    "anes",
    "enam",
    "fence",
    "mele",
    "mane",
    "lienee",
    "mensa",
    "ale",
    "sao",
    "esne",
    "alif",
    "amsel",
    "oasal",
    "fennec",
    "aulos",
    "manas",
    "ceil",
    "lues",
    "lee",
    "seaman",
    "nam",
    "aam",
    "oleo",
    "lue",
    "san",
    "olease",
    "cease",
    "asem",
    "fee",
    "sie",
    "sma",
    "ula",
    "name",
    "snee",
    "ean",
    "fils",
    "mensal",
    "enlife",
    "anan",
    "osela",
    "alienee",
    "ameen",
    "see",
    "clem",
    "nea",
    "els",
    "nana",
    "neese",
    "soe",
    "aes",
    "alose",
    "enema",
    "sal",
    "asana",
    "enfile",
    "iao",
    "sea",
    "mas",
    "feces",
    "nese",
    "eel",
    "soli",
    "oes",
    "melene",
    "alec",
    "lose",
    "meso",
    "soul",
    "clee",
    "aloose",
    "semen",
    "nasal",
    "sool",
    "anna",
    "manna",
    "lasa",
    "mesne",
    "meio",
    "lei",
    "scene",
    "ense",
    "senam",
    "lie",
    "ens",
    "easel",
    "nef",
    "ose",
    "soleas",
    "anele",
    "fice",
    "sola",
    "sole",
    "lens",
    "also",
    "leu",
    "sloo",
    "fisc",
    "ice",
    "manso",
    "sol",
    "amene",
    "ame",
    "seance",
    "sam"
  ],
  "rule_text": "all-ways! -- End of the the letters words. Specifically: consonants -- These words are all: verbs. -- ",
  "time_s": 810,
  "text_fully_revealed_at_s": 90,
  "number_of_words": 9,
  "uniqueness": 0.9129485756566778,
  "difficulty": 124.29999999999998
}