{"board": [["E", "Y", "I"], ["R", "F", "K"], ["N", "O", "E"]], "valid": ["reef", "fire", "keen", "free", "ink", "kern", "iron", "fink", "yoke", "yen", "reek", "oink", "rein", "irk", "knife", "key", "fin", "fine", "reify", "fry", "fork", "fee", "infer", "eye"], "invalid": ["froe", "info", "kef", "fen", "kirn", "ferie", "noy", "nero", "freen", "ree", "nee", "yeni", "roky", "keef", "nor", "irony", "kieye", "eery", "nro", "yne", "rekey", "krone", "infree", "kerne", "oie", "irok", "eyne", "nere", "reyoke", "renk", "fir", "noir", "oneyer", "kon", "ere", "rink", "foy", "finery", "nef", "kir", "ore", "neer", "fren", "foin", "ron", "yoi", "eyen", "erie", "yerk", "oer", "inyoke", "oke", "ken", "irone", "fiery", "yeo", "yore", "kier", "nek", "ferkin", "ney", "yoni", "okey", "knifer", "roe", "fineer", "ifree", "renky", "oni", "oner", "nik", "fey", "yirk", "erke", "yoe", "eyn", "rife", "fei", "nike", "kine", "ion", "foe", "neo", "forky", "ofer", "inker", "nife", "feer", "eire", "fern", "eiry", "fyke", "ferine", "ike", "roey", "kefir", "fer", "foyer", "knee", "yok", "rio", "kerf", "fie", "fikey", "erk", "ferk", "eyre", "erin", "ikon", "yern", "reefy", "eyren", "kino", "kernoi", "inr", "kye", "yfere", "yer", "nei", "korin", "yonker", "ferny", "fikery", "yee", "rie", "onker", "ony", "nye", "keyer", "inky", "enki", "eyer", "rokey", "eyrie", "ryen", "yon", "eke", "for", "fone", "yike", "orkey", "firn", "kyrine", "orfe", "erne", "kor", "ior", "fore", "eyr", "kero", "refine", "ref", "enfork", "onery", "firk", "eikon", "kore", "eer", "een", "keno", "kerion", "rye", "oik", "roke", "reeky", "yere", "fike", "kin", "ife", "reif", "reno", "ornify", "feyer", "enfire", "noire", "koi", "fri", "one", "rine", "erf", "fro", "reink", "york", "rone", "oyer", "orf", "roi", "roin", "inro", "ine", "ier", "okee", "ene", "neif", "oker", "kie", "eon", "firy", "ory", "nori", "frey", "yirn", "yoker", "frokin", "irene", "ikey", "yin", "reen", "ern", "finer", "freon", "rei", "eir", "yor", "eker", "norie", "ery", "ire", "rin", "koine", "oki", "ryke", "kori", "iyo", "ineye", "oken", "fere", "ify", "finky", "frike", "rokee", "frye", "ein"], "rule_text": "inside+wrap -- Words with at least 5 letters. -- These words are all: verbs. -- ", "time_s": 1152.0, "text_fully_revealed_at_s": 90, "number_of_words": 16, "uniqueness": 0.6304159445407279, "difficulty": 1012.5}