{"board": [["B", "A", "H"], ["L", "L", "B"], ["S", "A", "W"], ["P", "R", "N"], ["O", "W", "L"], ["Y", "O", "D"]], "valid": ["nro", "orna", "rna", "spa", "baba", "pro", "bap", "lwop", "sapo", "dowp", "nabla", "saba", "hala", "rasp", "orlo", "ora", "asp", "loop", "lap", "sarpo", "aba", "nap", "wasp", "loo", "arp", "nra", "sala", "slap", "sap", "woo", "doo", "roo", "sla", "walla", "wop", "wrap", "psa", "downwarp", "ala", "alba", "paba", "wro", "proo", "rap", "napoo", "wap", "palla", "yoop", "warp", "balsa"], "invalid": ["lan", "par", "blaw", "paw", "spawn", "slab", "wraps", "alw", "bars", "oral", "span", "awl", "lod", "spool", "blas", "woops", "arow", "abls", "allah", "bas", "alan", "rool", "raw", "warn", "wraw", "allan", "rabal", "sabah", "woy", "owd", "low", "salal", "sawn", "ran", "wran", "law", "wallah", "awn", "opals", "oras", "ors", "alar", "nar", "babar", "sporal", "world", "laban", "all", "awls", "wood", "llb", "alban", "wold", "balas", "hals", "row", "nab", "rowy", "alls", "was", "dowy", "lhb", "pallah", "sabal", "san", "doors", "prawn", "barn", "dow", "asl", "wars", "alas", "wan", "rall", "yor", "ball", "lab", "wod", "bawl", "pal", "sal", "loy", "bawn", "prowl", "wlan", "rab", "wall", "balls", "prow", "hallan", "las", "ban", "sapor", "dol", "bar", "bah", "pan", "yowl", "blawn", "ballan", "lablab", "babas", "yod", "pars", "woold", "warps", "rals", "bals", "wrawl", "pool", "spall", "blah", "lnr", "salah", "spar", "raps", "bawls", "saw", "nallah", "baw", "lbw", "hall", "prn", "bal", "poral", "poy", "albas", "pall", "pawl", "wops", "porn", "own", "lar", "blab", "old", "abl", "halas", "oran", "warlow", "lawn", "naw", "sab", "ras", "orals", "rood", "wab", "arn", "narw", "rwd", "wool", "barwood", "nrl", "pas", "larn", "spawl", "pood", "apr", "halab", "worn", "dowl", "spor", "sprawl", "alb", "ballas", "laps", "dlr", "pow", "barlow", "war", "blan", "down", "bwr", "door", "slaw", "lah", "ops", "lowy", "orl", "als", "sar", "owl", "opal", "naps", "yow", "pawn", "sapwood", "pawls", "wnw", "aprowl", "abas", "waps", "palls", "pwr", "warl", "lown", "halal"], "rule_text": "inside -- Ends with a letter from potato -- ", "time_s": 180.0, "text_fully_revealed_at_s": 90, "number_of_words": 5, "uniqueness": 0.5339805825242718, "difficulty": 578.5}