{"board": [["U", "E", "U", "O", "A", "A", "I"], ["E", "W", "A", "E", "E", "U", "N"], ["G", "B", "A", "I", "O", "S", "A"], ["R", "N", "A", "B", "G", "E", "M"], ["L", "N", "E", "I", "L", "N", "W"], ["A", "O", "R", "N", "H", "W", "E"], ["T", "E", "X", "F", "R", "E", "O"]], "valid": ["name", "mas", "rein", "bilge", "nab", "biogen", "bilges", "norn", "names", "samen", "manus", "masu", "goi", "sam", "sue", "men", "late", "nam", "lie", "mani", "sun", "san", "biose", "biog", "reno", "nro", "tal", "werf", "man", "mania", "sog", "latex", "wer", "nea", "baa", "naso", "bier", "lienor", "seg", "noa", "tao", "soe", "meg", "lao", "rei", "nib", "nein", "rone", "gos", "nasua", "wnw", "binh", "renn", "sego", "lat", "nil", "wbn", "lier", "bin", "nor", "nema", "lien", "nne", "noex", "rna", "nrl", "nemas", "rea", "same", "lgb", "nae", "glib", "bien", "lin", "sen", "wae", "bai", "whr", "mesa", "nero", "mesua", "naa", "banner", "nbw", "nei", "gen", "roe", "gem", "meso", "bio", "ron", "bae", "ban", "bios"], "invalid": ["oer", "aeron", "ego", "asem", "egos", "one", "enorn", "awe", "use", "anne", "iba", "anno", "usa", "abn", "inro", "oat", "ern", "oie", "eta", "ewe", "eon", "aer", "ase", "eos", "ewer", "anba", "inh", "aero", "ose", "alnein", "exr", "erf", "amen", "iaa", "ein", "aor", "oner", "anu", "ore", "eib", "ani", "ina", "enl", "ain", "aln", "ann", "inr", "ate", "ean", "ier", "aaa", "ame", "anus"], "rule_text": "directions: E W N S  -- The first part of the word is important. Is one of : consonants -- ", "time_s": 1863.0, "text_fully_revealed_at_s": 90, "number_of_words": 23, "uniqueness": 0.4243421052631579, "difficulty": 1056.0}