{"board": [["O", "O", "G", "Z"], ["N", "O", "R", "V"], ["I", "H", "B", "E"], ["B", "B", "R", "A"], ["I", "N", "O", "T"], ["L", "E", "T", "E"], ["I", "U", "N", "Y"], ["O", "M", "O", "S"]], "valid": ["oon", "broo", "orae", "hor", "nota", "orb", "nom", "nib", "monte", "net", "brat", "eat", "rota", "eta", "tetel", "ony", "tora", "bra", "sye", "inorg", "teton", "arb", "tone", "ium", "leu", "yeta", "leno", "mon", "mun", "nete", "tot", "ono", "org", "nil", "inorb", "binet", "oil", "rot", "brot", "one", "brae", "ate", "tete", "eyn", "tote", "moile", "let", "orate", "moil", "hin", "munt", "leto", "bile", "onto", "som", "tor", "ton", "bine", "ten", "lete", "unto", "rone", "bear", "lino", "neum", "nile", "nosy", "goon", "rote", "lin", "beat", "ont", "atone", "ear", "ron", "goo", "ator", "ora", "ine", "ote", "nomoi", "nor", "nih", "tet", "bilio", "tarot", "ileum", "taro", "line", "mony", "tar", "oni", "rate", "ile", "ooh", "not", "bin", "tenor", "note", "ilium", "ebro", "nyet", "yet", "roo", "noo", "nye", "son", "eten", "aton", "tae", "rat", "teli", "bino"], "invalid": ["syntone", "ineunt", "brotel", "monton", "libbra", "norate", "untone", "telium", "letorate"], "rule_text": "directions: E W N S  -- At least 5 of da letters. -- ", "time_s": 2592.0, "text_fully_revealed_at_s": 90, "number_of_words": 32, "uniqueness": 0.0, "difficulty": 1057.5}