{"board": [["W", "P", "V", " ", " ", " ", " "], ["S", "T", "B", " ", " ", " ", " "], ["O", "O", "R", " ", " ", " ", " "], ["E", "D", "E", " ", " ", " ", " "], ["B", "X", "E", "P", "E", "N", "S"], ["E", "S", "U", "N", "E", "V", "T"]], "valid": ["dexes", "deer", "dep", "env", "wese", "wto", "debs", "ene", "evene", "esne", "does", "deeses", "neper", "need", "dene", "dot", "ense", "epees", "edo", "erd", "exert", "neep", "den", "webs", "wept", "deb", "dee", "web", "desexes", "doer", "dor", "doest", "erodes", "dost", "deepens", "dreep", "dos", "doo", "debts", "ens", "nese", "dob", "doob", "event", "events", "enent", "exerts", "eros", "dero", "wtv", "eos", "ened", "eses", "est", "neer", "dorts", "depe", "ese", "dees", "evened", "eer", "esp", "door", "nep", "dree", "neve", "exede", "wets", "evens", "nexus", "desex", "deep", "exes", "nene", "eden", "deux", "erode", "neven", "wet", "doree", "ebs", "drees", "ert", "doesn", "epee", "eve", "nenes", "ent", "deepen", "doesnt", "nee", "doe", "des", "west", "een", "debe", "even", "debt", "nexuses"], "invalid": ["bse", "bodes", "spues", "sort", "broo", "per", "soree", "tree", "boot", "sexes", "supes", "penes", "beden", "orb", "toed", "stews", "brede", "sune", "ordene", "peens", "swept", "bpt", "stept", "sexed", "toes", "booed", "uptree", "redo", "unp", "spued", "roes", "pts", "suedes", "pen", "sot", "roots", "bot", "strep", "pee", "pst", "pews", "reese", "boden", "sepn", "tbsp", "bood", "boree", "boost", "tode", "ored", "bredes", "superb", "soe", "bps", "redos", "broos", "stoep", "bos", "boe", "brees", "usee", "see", "bots", "sebs", "rob", "sebe", "spews", "tew", "stp", "rod", "uneven", "besee", "sup", "tod", "rooed", "stree", "veepee", "rodeos", "ordo", "bode", "pedros", "rodeo", "sordo", "unpens", "sew", "sord", "boer", "rexen", "bets", "upset", "trees", "rot", "brot", "trode", "pedro", "brod", "ordos", "oes", "stepup", "seor", "bod", "treed", "stood", "strode", "streen", "repent", "sen", "repents", "store", "pet", "super", "used", "bedeen", "pert", "sex", "sept", "pes", "beode", "peer", "repen", "rede", "rtw", "stew", "rexes", "usps", "breed", "sep", "veneer", "bede", "peed", "borts", "best", "suv", "veen", "twp", "spun", "beset", "venues", "pedes", "xed", "sorex", "strepent", "uptore", "stod", "spt", "sets", "venene", "oort", "treen", "roost", "tor", "bred", "bxs", "reen", "pede", "venue", "oots", "seer", "snee", "pwt", "odor", "ore", "seed", "bore", "spue", "soord", "pens", "sue", "trod", "venus", "streep", "upboost", "ode", "bvt", "boreen", "sews", "oto", "swep", "rep", "oer", "pent", "boo", "bored", "besew", "stored", "too", "oder", "sued", "pets", "sordes", "septs", "oos", "ree", "pees", "upbreed", "seep", "stob", "redes", "use", "steps", "suede", "superdebt", "otoe", "veepees", "sore", "soot", "bort", "punese", "seps", "pew", "psuedo", "penup", "red", "bed", "peened", "str", "boos", "sene", "rex", "bedot", "ped", "sob", "boots", "spex", "spew", "peen", "pedeses", "bepun", "puses", "supe", "sorb", "veep", "pups", "brosot", "upstood", "obv", "rode", "roe", "sups", "set", "oed", "peneus", "roto", "bedene", "oord", "stor", "stooden", "pup", "seb", "reed", "tore", "peert", "unpen", "sbe", "root", "rood", "pest", "bes", "unpent", "vents", "vee", "ort", "roo", "upbore", "sun", "sod", "boder", "strepen", "upbred", "pun", "redoes", "rotos", "step", "toe", "pus", "bor", "pto", "bet", "storeen", "pense", "tored", "odo", "roed", "stre", "seder", "odes", "orts", "stbd", "spet", "brodee", "upsets", "bord", "bree", "vent", "brood"], "rule_text": "inside+wrap -- The first part of the word is important. Is one of : wedding -- ", "time_s": 2160.0, "text_fully_revealed_at_s": 90, "number_of_words": 30, "uniqueness": 0.5143769968051118, "difficulty": 1105.5}