{"board": [["Z", "Y", "H", "B"], ["E", "E", "E", "I"], ["Q", "C", "I", "N"], ["S", "I", "L", "D"]], "valid": ["qin", "enid", "nib", "bins", "din", "bee", "nihil", "lids", "lin", "enl", "zen", "beys", "lice", "nil", "size", "bens", "hinds", "bends", "hili", "bend", "zend", "eye", "lien", "bize", "lie", "behinds", "hebe", "hdl", "cis", "nsc", "ney", "niece", "nebe", "iis", "neb", "hin", "yens", "hebei", "dins", "scid", "scene", "sneeze", "yis", "nibs", "ics", "liens", "bind", "binds", "lye", "ins", "hen", "ends", "cline", "nih", "biz", "hindi", "line", "bin", "sbe", "eib", "hins", "indie", "cid", "cli", "iqs", "zib", "indic", "nec", "sild", "yen", "blinds", "bine", "lid", "lis", "ice", "dice", "sicily", "hind", "blind", "zee", "eec", "end", "iii", "hens", "blini", "ben", "eblis", "die", "nice", "lind", "ene", "ebs", "bey", "behind", "isn", "ens"], "invalid": ["snee", "hiney", "beice", "sic", "nei", "snib", "heild", "hendly", "zeins", "inly", "sylid", "dieb", "heize", "liney", "lys", "dine", "hisn", "nee", "blin", "bien", "ihi", "nizey", "bld", "lhb", "isz", "ine", "dilis", "hld", "hie", "hend", "nid", "een", "lyze", "zein", "beylics", "beni", "beylic", "bhindi", "cize", "hyenic", "zineb", "heii", "neeze", "heezie", "niblic", "indice", "heeze", "biens", "sye", "hee", "ize", "bdl", "hey", "hei", "beild", "bezil", "scind", "ecize", "lii", "sizy", "beinly", "cene", "scend", "cebine", "eyl", "ineye", "yee", "lienee", "idly", "cee", "icily", "sneb", "bensil", "ceil", "liii", "bhd", "liin", "heezy", "hine", "zebecs", "sqd", "linie", "yeni", "nizy", "sneezy", "bienly", "bec", "heily", "benic", "cly", "sil", "indii", "hyli", "hylids", "dbl", "ein", "hylic", "scil", "heben", "clin", "yez", "heil", "hic", "eneid", "zinebs", "liq", "nici", "bene", "bindi", "sice", "syli", "dicey", "sizeine", "diene", "eild", "eyen", "cine", "his", "zebec"], "rule_text": "inside+wrap -- These words are all: nouns. -- ", "time_s": 648.0, "text_fully_revealed_at_s": 90, "number_of_words": 18, "uniqueness": 0.5257995735607676, "difficulty": 608.5}