{"board": [["S", "D", "T"], ["E", "A", "L"], ["L", "I", "S"], ["I", "N", "O"], ["U", "H", "I"], ["S", "I", "C"], ["Y", "E", "N"], ["L", "O", "S"], ["D", "U", "A"]], "valid": ["ileal", "eld", "ise", "ich", "eos", "inchon", "echinus", "ins", "insol", "ensoul", "ionic", "ionia", "echo", "ein", "iis", "insoles", "ice", "ead", "ish", "ela", "inc", "eons", "iyo", "edta", "ial", "ichu", "ilial", "ied", "inh", "eyl", "iliad", "iliads", "ions", "echos", "elisa", "ichs", "iso", "eous", "eln", "eas", "elia", "ile", "elod", "eila", "enc", "elain", "ices", "echini", "eshin", "esau", "ilion", "inla", "inial", "insole", "ens", "ihi", "ison", "inch", "elains", "icho", "eon", "ion", "insoul", "ine", "eds", "eild", "enol", "ilia", "isn", "eat"], "invalid": ["doney", "noil", "noel", "sad", "sla", "sas", "uns", "lone", "uhs", "duo", "aln", "selion", "ley", "souly", "sud", "ones", "lades", "noa", "oiled", "nsu", "asl", "lie", "hun", "dail", "leads", "doses", "yield", "noyes", "das", "chiliads", "unio", "huse", "lied", "chinol", "sion", "sie", "sine", "hin", "chi", "yous", "ailed", "tali", "tael", "use", "chuse", "tain", "lench", "ush", "unlead", "silt", "sinus", "ludo", "nold", "slt", "oni", "yis", "since", "deals", "slat", "delius", "unlade", "lii", "loa", "lye", "sol", "cion", "dale", "dea", "chisel", "lysins", "sech", "lain", "shield", "chins", "hine", "ali", "linie", "dali", "sonchus", "suine", "chun", "seoul", "onus", "youd", "also", "honied", "tale", "yins", "deasil", "solei", "sil", "louses", "ousel", "chil", "chinoa", "lyon", "soud", "shine", "oeci", "suld", "chis", "sedat", "unlie", "chiliad", "nice", "ain", "tald", "sec", "nici", "lei", "yech", "cho", "sice", "lea", "lai", "nouses", "dae", "sone", "ose", "nose", "once", "lion", "tal", "shin", "sen", "chon", "done", "unlades", "shiel", "shi", "oleic", "dosa", "sey", "tailed", "donec", "chile", "nould", "shun", "lin", "lesiy", "tade", "doyens", "oud", "lys", "alii", "oleins", "hili", "tails", "neo", "slae", "lysine", "deils", "sencio", "leys", "doesn", "snodly", "oils", "dal", "udo", "ohs", "asio", "loses", "olein", "unoiled", "unleads", "sial", "yin", "slade", "lies", "oses", "usn", "sens", "sun", "soy", "uniat", "alin", "dalt", "dat", "sensa", "sains", "shines", "unsalt", "ails", "dle", "duole", "cns", "yes", "sich", "don", "shins", "lads", "aud", "dain", "chn", "oases", "seis", "oii", "lade", "lech", "lechosa", "choile", "seat", "sai", "tae", "nod", "oncin", "talio", "unsailed", "yen", "unled", "oyes", "noy", "sal", "yod", "cineol", "leds", "lis", "sld", "ous", "dolus", "lyons", "dais", "you", "usa", "sinhs", "oles", "duly", "yechs", "oas", "noecho", "nesh", "hic", "lilt", "unleal", "ois", "hsien", "chiel", "unsoiled", "tales", "onces", "doei", "sin", "duos", "suns", "leon", "hus", "luo", "sea", "cine", "sod", "dasi", "ulose", "noes", "nei", "nodus", "aul", "ons", "old", "sines", "son", "liles", "aliso", "las", "hield", "led", "louse", "soul", "does", "yonis", "nodules", "nousel", "aiel", "sades", "cio", "sonic", "dals", "tad", "soles", "talions", "deal", "hie", "leno", "leda", "yoe", "lead", "alnus", "lenis", "nile", "lens", "soys", "leat", "delis", "lad", "lased", "dealt", "aion", "leo", "dase", "als", "oil", "shice", "dons", "dos", "cise", "unie", "deil", "leal", "nous", "nihon", "lysines", "sencion", "des", "alt", "sales", "yon", "shuns", "ade", "oes", "tains", "yonic", "yeso", "noses", "sat", "nih", "nsa", "sile", "dose", "taled", "soe", "nichil", "hila", "snies", "chin", "asin", "talionic", "ale", "unsad", "hins", "chili", "tads", "sals", "liin", "secno", "saone", "sauld", "yeo", "chs", "cinel", "season", "yoni", "hile", "seld", "nicely", "ceo", "huic", "ule", "sho", "lile", "yeld", "chield", "niceish", "alnuin", "sailed", "solen", "seals", "nosey", "chinles", "lyses", "sao", "unl", "chios", "talis", "dasein", "his", "chinois", "lat", "hiney", "slain", "aile", "sic", "douses", "chinos", "talion", "doni", "youl", "nol", "nihil", "ains", "solein", "shies", "douse", "hies", "lase", "sain", "nil", "doe", "duse", "ase", "salt", "saul", "ole", "donis", "nodule", "ales", "sole", "ouse", "ail", "cis", "sails", "ney", "liason", "one", "alison", "deinos", "chien", "deli", "deia", "lod", "chinse", "auld", "doles", "aes", "tail", "yens", "lino", "sinh", "sones", "nou", "sye", "dole", "sold", "unsoil", "lysin", "ceylon", "yodles", "deis", "usine", "aulos", "seal", "usnic", "noils", "oic", "lose", "lenos", "huns", "youse", "satd", "loy", "soil", "snod", "udos", "soiled", "sale", "sade", "nec", "sensu", "sild", "sou", "yeni", "unoil", "tai", "sail", "chines", "sinuses", "doyen", "lyes", "chino", "choil", "cines", "ainoi", "onuses", "slad", "dol", "senso", "hoin", "loud", "tainos", "deas", "soh", "hoi", "huile", "sasin", "unice", "oie", "chine", "cions", "desalt", "yince", "yodle", "silds", "lyse", "chilies"], "rule_text": "inside -- The first part of the word is important. Is one of : mike -- ", "time_s": 864.0, "text_fully_revealed_at_s": 90, "number_of_words": 12, "uniqueness": 0.5366666666666666, "difficulty": 1150.0}