{
  "board": [
    [
      "I",
      "E",
      "N"
    ],
    [
      "E",
      "U",
      "N"
    ],
    [
      "S",
      "E",
      "H"
    ],
    [
      "T",
      "I",
      "H"
    ],
    [
      "A",
      "C",
      "T"
    ],
    [
      "E",
      "S",
      "S"
    ],
    [
      "R",
      "Y",
      "L"
    ],
    [
      "I",
      "E",
      "E"
    ]
  ],
  "valid": [
    "tithe",
    "ice",
    "cere",
    "ace",
    "tie",
    "site",
    "case",
    "eye",
    "tee",
    "hie",
    "see",
    "ache",
    "cite",
    "use",
    "sue",
    "sate",
    "recite",
    "ate",
    "hue"
  ],
  "invalid": [
    "erect",
    "stith",
    "this",
    "yest",
    "schene",
    "cest",
    "rely",
    "restis",
    "sithe",
    "sri",
    "sai",
    "tai",
    "cista",
    "chien",
    "sleer",
    "cast",
    "eche",
    "thee",
    "chi",
    "its",
    "hitch",
    "ten",
    "sect",
    "sunn",
    "caser",
    "cate",
    "chest",
    "lysate",
    "sic",
    "tche",
    "schist",
    "aitch",
    "tsere",
    "cess",
    "seat",
    "seen",
    "reach",
    "set",
    "ich",
    "sat",
    "ser",
    "theist",
    "nese",
    "hist",
    "achene",
    "nun",
    "het",
    "aesthetic",
    "yeast",
    "eyer",
    "eta",
    "tae",
    "sith",
    "hit",
    "setae",
    "ust",
    "ast",
    "hicatee",
    "eyre",
    "aesthetics",
    "ach",
    "nei",
    "asci",
    "taich",
    "tait",
    "sey",
    "sit",
    "tice",
    "neist",
    "east",
    "ase",
    "cise",
    "ire",
    "hetaery",
    "ere",
    "these",
    "tach",
    "atis",
    "lee",
    "his",
    "yee",
    "sac",
    "unnest",
    "recti",
    "itch",
    "cass",
    "ess",
    "tch",
    "hest",
    "hiate",
    "leery",
    "eer",
    "saithe",
    "sere",
    "taise",
    "scat",
    "ree",
    "sune",
    "ectene",
    "rie",
    "tache",
    "reasy",
    "ley",
    "lyse",
    "ass",
    "sea",
    "sachet",
    "seta",
    "stchi",
    "rel",
    "restitch",
    "theta",
    "ascites",
    "ates",
    "aery",
    "sun",
    "aer",
    "tenues",
    "leer",
    "tsun",
    "sec",
    "chih",
    "rest",
    "recta",
    "hithe",
    "cit",
    "ceryl",
    "cistae",
    "eats",
    "sitch",
    "thetic",
    "easy",
    "saic",
    "sie",
    "eaten",
    "sice",
    "tenne",
    "sye",
    "citee",
    "sectist",
    "tass",
    "nee",
    "recast",
    "ist",
    "tien",
    "astite",
    "act",
    "ait",
    "huse",
    "sech",
    "thetics",
    "chee",
    "eyereach",
    "yes",
    "aes",
    "stitch",
    "esthesia",
    "neti",
    "stite",
    "lyssa",
    "tic",
    "yea",
    "reel",
    "lys",
    "eel",
    "unhit",
    "each",
    "rect",
    "cist",
    "seit",
    "hia",
    "lye",
    "sley",
    "lei",
    "rea",
    "sceat",
    "ctene",
    "hei",
    "eyrie",
    "then",
    "stich",
    "eely",
    "tsia",
    "chia",
    "hic",
    "sen",
    "sten",
    "else",
    "syre",
    "suet",
    "aerie",
    "the",
    "tacit",
    "net",
    "yeat",
    "tact",
    "eat",
    "yere",
    "ennui",
    "slee",
    "sly",
    "sleyer",
    "ticer",
    "ers",
    "neese",
    "etch",
    "els",
    "rye",
    "chit",
    "esca",
    "che",
    "tit",
    "usee",
    "staith",
    "yeel",
    "unhitch",
    "yer",
    "tite",
    "cat",
    "scase",
    "hen",
    "lyre",
    "react",
    "nest"
  ],
  "rule_text": "inside -- These words seem to end with the letters... mike. -- These words are all: verbs. -- ",
  "time_s": 990,
  "text_fully_revealed_at_s": 90,
  "number_of_words": 11,
  "uniqueness": 1.1067125320722444,
  "difficulty": 184.5
}