{"board": [["A", "S", "S", "I", "S", "H"], ["D", "E", "S", "A", "L", "T"], ["E", "N", "F", "E", "C", "T"], ["K", "N", "A", "W", "E", "L"], ["H", "A", "N", "G", "U", "P"], ["I", "T", "H", "U", "N", "N"], ["G", "Y", "R", "E", "N", "E"], ["O", "P", "I", "A", "N", "E"]], "valid": ["alt", "wan", "knawel", "lew", "ssa", "assis", "unn", "ish", "ithunn", "hang", "pug", "ass", "pian", "ery", "knaw", "naw", "opia", "han", "lased", "las", "ect", "ane", "pia", "lase", "ene", "sis", "sish", "gyre", "wank", "opiane", "ase", "enfect", "salt", "ngu", "ipo", "ian", "desalt", "knawe", "gyrene", "ang", "gup", "sal", "tce", "assi", "awe", "assish", "hangup", "hun", "siss", "des"], "invalid": [], "rule_text": "directions: E W  -- ", "time_s": 432.0, "text_fully_revealed_at_s": 90, "number_of_words": 8, "uniqueness": 0.0, "difficulty": 656.0}