{
  "board": [
    [
      "H",
      "W",
      "O",
      "Y",
      "R",
      "R",
      "B",
      "U"
    ],
    [
      "E",
      "N",
      "L",
      "O",
      "G",
      "B",
      "O",
      "A"
    ],
    [
      "V",
      "A",
      "E",
      "G",
      "G",
      "N",
      "B",
      "H"
    ],
    [
      "D",
      "T",
      "O",
      "E",
      "T",
      "U",
      "O",
      "T"
    ],
    [
      "U",
      "E",
      "C",
      "V",
      "T",
      "O",
      "O",
      "I"
    ],
    [
      "Q",
      "E",
      "O",
      "E",
      "E",
      "A",
      "N",
      "A"
    ],
    [
      "N",
      "A",
      "D",
      "Y",
      "Z",
      "O",
      "R",
      "W"
    ],
    [
      "S",
      "C",
      "Z",
      "L",
      "A",
      "N",
      "E",
      "G"
    ]
  ],
  "valid": [
    "wait",
    "dye",
    "get",
    "out",
    "bob",
    "laze",
    "lean",
    "can",
    "cod",
    "own",
    "tee",
    "leave",
    "vet",
    "boo",
    "nut",
    "wan",
    "log",
    "eat",
    "toe",
    "gel",
    "zone",
    "tan",
    "leaven",
    "scan",
    "ate",
    "tout",
    "egg",
    "low"
  ],
  "invalid": [
    "eloge",
    "vee",
    "enate",
    "ady",
    "tave",
    "bobo",
    "naw",
    "zee",
    "geo",
    "gen",
    "grr",
    "tun",
    "due",
    "roan",
    "lown",
    "gog",
    "toco",
    "leat",
    "oleo",
    "geat",
    "ion",
    "duet",
    "vat",
    "tec",
    "nael",
    "tae",
    "eta",
    "lane",
    "lan",
    "gnu",
    "tha",
    "nave",
    "dae",
    "ger",
    "doe",
    "orna",
    "boa",
    "eve",
    "ona",
    "cot",
    "tane",
    "both",
    "van",
    "yee",
    "ore",
    "bout",
    "ave",
    "toon",
    "toa",
    "scad",
    "azon",
    "yeo",
    "wren",
    "wro",
    "oda",
    "lea",
    "ocote",
    "aly",
    "zoa",
    "one",
    "azo",
    "tean",
    "gol",
    "anoa",
    "cetane",
    "odyl",
    "lazy",
    "nae",
    "oleate",
    "goy",
    "loy",
    "too",
    "gena",
    "zonal",
    "naze",
    "ego",
    "ait",
    "hao",
    "gean",
    "dan",
    "ean",
    "coda",
    "tav",
    "hen",
    "cad",
    "teg",
    "lye",
    "tael",
    "yow",
    "egol",
    "boun",
    "loge",
    "leg",
    "when",
    "ana",
    "tez",
    "coe",
    "renal",
    "boon",
    "oner",
    "adz",
    "bot",
    "tea",
    "rone",
    "nat",
    "naio",
    "cote",
    "hau",
    "reg",
    "vane",
    "tung",
    "nor",
    "doc",
    "tou",
    "noa",
    "aion",
    "cee",
    "woy",
    "genal",
    "quet",
    "ado",
    "eave"
  ],
  "rule_text": "directions: ️E️️WN️S️ -- OMG,these are: verbs -- ",
  "time_s": 1530,
  "text_fully_revealed_at_s": 90,
  "number_of_words": 17,
  "uniqueness": 0.5962230215827338,
  "difficulty": 121.5
}